pycofecms/__init__.py
pycofecms/api.py
pycofecms-0.1.1.dist-info/DESCRIPTION.rst
pycofecms-0.1.1.dist-info/METADATA
pycofecms-0.1.1.dist-info/RECORD
pycofecms-0.1.1.dist-info/WHEEL
pycofecms-0.1.1.dist-info/metadata.json
pycofecms-0.1.1.dist-info/top_level.txt
