Metadata-Version: 2.0
Name: pycofecms
Version: 0.1.1
Summary: Church of England CMS API Client
Home-page: https://github.com/developersociety/pycofecms
Author: The Developer Society
Author-email: studio@dev.ngo
License: BSD license
Keywords: cofecms
Platform: UNKNOWN
Classifier: Development Status :: 2 - Pre-Alpha
Classifier: Intended Audience :: Developers
Classifier: License :: OSI Approved :: BSD License
Classifier: Natural Language :: English
Classifier: Programming Language :: Python :: 3.5
Requires-Python: >=3.5
Requires-Dist: requests (>=2.0.0)
